indonesia/__init__.py
indonesia-0.0.0.dist-info/LICENSE
indonesia-0.0.0.dist-info/METADATA
indonesia-0.0.0.dist-info/WHEEL
indonesia-0.0.0.dist-info/top_level.txt
indonesia-0.0.0.dist-info/RECORD
