Metadata-Version: 2.1
Name: indonesia
Version: 0.0.0
Summary: Initial indonesia package.
Home-page: https://github.com/nggit/indonesia
Author: nggit
Author-email: contact@anggit.com
License: MIT
Classifier: Development Status :: 3 - Alpha
Classifier: License :: OSI Approved :: MIT License
Classifier: Operating System :: OS Independent
Classifier: Topic :: Software Development :: Libraries
License-File: LICENSE
